{
  "Parent": "Soil_Gravel_Half",
  "TranslationProperties": {
    "Name": "server.items.Soil_Lime_Gravel_Half.name"
  },
  "Icon": "Icons/ItemsGenerated/Soil_Lime_Gravel_Half.png",
  "Categories": [
    "Blocks.Rocks"
  ],
  "Set": "Rock_Lime",
  "Interactions": {
    "Secondary": {
      "Interactions": [
        {
          "Parent": "Half_Block",
          "Matchers": [
            {
              "Block": {
                "Id": "Soil_Lime_Gravel_Half",
                "State": "default"
              },
              "Face": "Up",
              "StaticFace": false
            }
          ]
        }
      ]
    }
  },
  "BlockType": {
    "CustomModelTexture": [
      {
        "Texture": "BlockTextures/Soil_Gravel_Limestone.png",
        "Weight": 1
      }
    ],
    "Gathering": {
      "Breaking": {
        "GatherType": "Soils",
        "DropList": "Soil_Gravel_Lime"
      }
    },
    "ParticleColor": "#dccd97",
    "State": {
      "Definitions": {
        "Block": {
          "Material": "Solid",
          "DrawType": "Cube",
          "HitboxType": "Full",
          "Textures": [
            {
              "All": "BlockTextures/Soil_Gravel_Limestone.png"
            }
          ],
          "Gathering": {
            "Breaking": {
              "GatherType": "Soils",
              "DropList": {
                "Container": {
                  "Type": "Single",
                  "Item": {
                    "ItemId": "Soil_Lime_Gravel_Half",
                    "QuantityMax": 2,
                    "QuantityMin": 2
                  }
                }
              }
            }
          }
        }
      }
    }
  },
  "IconProperties": {
    "Scale": 0.58823,
    "Rotation": [
      22.5,
      45,
      22.5
    ],
    "Translation": [
      0,
      -13.5
    ]
  }
}